deepmost/__init__.py
deepmost/prospecting.py
deepmost/sales.py
deepmost/core/__init__.py
deepmost/core/embeddings.py
deepmost/core/predictor.py
deepmost/core/utils.py
deepmost-0.5.2.dist-info/licenses/LICENSE
deepmost-0.5.2.dist-info/METADATA
deepmost-0.5.2.dist-info/WHEEL
deepmost-0.5.2.dist-info/top_level.txt
deepmost-0.5.2.dist-info/RECORD
