Metadata-Version: 2.4
Name: deepmost
Version: 0.5.2
Summary: Sales conversion prediction and prospecting using reinforcement learning and AI agents.
Author-email: DeepMost Innovations <support@deepmostai.com>
License: MIT License
Project-URL: Homepage, https://github.com/DeepMostInnovations/deepmost
Project-URL: Bug Reports, https://github.com/DeepMostInnovations/deepmost/issues
Project-URL: Source, https://github.com/DeepMostInnovations/deepmost
Project-URL: Documentation, https://deepmost.readthedocs.io/
Project-URL: Model Repository, https://huggingface.co/DeepMostInnovations
Keywords: sales,prospecting,conversion,prediction,reinforcement-learning,ai,machine-learning,llm,nlp,gguf,agents
Classifier: Development Status :: 4 - Beta
Classifier: Intended Audience :: Developers
Classifier: Topic :: Scientific/Engineering :: Artificial Intelligence
Classifier: License :: OSI Approved :: MIT License
Classifier: Programming Language :: Python :: 3
Classifier: Programming Language :: Python :: 3.10
Classifier: Programming Language :: Python :: 3.11
Classifier: Programming Language :: Python :: 3.12
Requires-Python: >=3.10
License-File: LICENSE
Requires-Dist: torch==2.7.1
Requires-Dist: transformers==4.52.3
Requires-Dist: stable-baselines3==2.6.0
Requires-Dist: gymnasium==1.1.1
Requires-Dist: numpy==2.4.0
Requires-Dist: requests==2.32.4
Requires-Dist: tqdm==4.67.1
Requires-Dist: huggingface_hub==0.34.4
Requires-Dist: openai==1.102.0
Requires-Dist: smolagents[toolkit]==1.19.0
Requires-Dist: accelerate==1.8.1
Provides-Extra: gpu
Requires-Dist: llama-cpp-python[server]>=0.3.9; extra == "gpu"
Provides-Extra: prospecting
Requires-Dist: smolagents[toolkit]>=1.19.0; extra == "prospecting"
Requires-Dist: accelerate>=1.8.1; extra == "prospecting"
Provides-Extra: dev
Requires-Dist: deepmost[gpu,prospecting]; extra == "dev"
Requires-Dist: pytest>=7.0.0; extra == "dev"
Requires-Dist: pytest-cov>=4.0.0; extra == "dev"
Requires-Dist: black>=23.0.0; extra == "dev"
Requires-Dist: isort>=5.10.0; extra == "dev"
Requires-Dist: flake8>=6.0.0; extra == "dev"
Requires-Dist: mypy>=1.0.0; extra == "dev"
Requires-Dist: ruff>=0.1.0; extra == "dev"
Dynamic: license-file
